<?xml version="1.0" encoding="utf-8"?>
<!--
Automatically generated IO group description. Please do NOT modify!
-->
<SunriseIOGroupDescription xmlns:xsi="http://www.w3.org/2001/XMLSchema-instance" xmlns:xsd="http://www.w3.org/2001/XMLSchema" Version="1.0.0">
  <IOGroup DisplayName="CognexProfinetIN" IconName="CognexProfinetIN" SignalTypes="InOut" TemplateName="CognexProfinetIN">
    <IOs>
      <DigitalIOItem Name="AcquisutionStatusReg0" DataType="BOOL" IOType="Input" UsedBitWidth="1" IsConnected="true">
        <Description />
      </DigitalIOItem>
      <DigitalIOItem Name="AcquisutionStatusReg1" DataType="BOOL" IOType="Input" UsedBitWidth="1" IsConnected="true">
        <Description />
      </DigitalIOItem>
      <DigitalIOItem Name="AcquisutionStatusReg2" DataType="BOOL" IOType="Input" UsedBitWidth="1" IsConnected="true">
        <Description />
      </DigitalIOItem>
      <DigitalIOItem Name="AcquisutionStatusReg3" DataType="BOOL" IOType="Input" UsedBitWidth="1" IsConnected="true">
        <Description />
      </DigitalIOItem>
      <DigitalIOItem Name="AcquisutionStatusReg4" DataType="BOOL" IOType="Input" UsedBitWidth="1" IsConnected="true">
        <Description />
      </DigitalIOItem>
      <DigitalIOItem Name="AcquisutionStatusReg5" DataType="BOOL" IOType="Input" UsedBitWidth="1" IsConnected="true">
        <Description />
      </DigitalIOItem>
      <DigitalIOItem Name="AcquisutionStatusReg6" DataType="BOOL" IOType="Input" UsedBitWidth="1" IsConnected="true">
        <Description />
      </DigitalIOItem>
      <DigitalIOItem Name="AcquisutionStatusReg7" DataType="BOOL" IOType="Input" UsedBitWidth="1" IsConnected="true">
        <Description />
      </DigitalIOItem>
      <DigitalIOItem Name="AcqCtrlReg0" DataType="BOOL" IOType="Output" UsedBitWidth="1" IsConnected="true">
        <Description />
      </DigitalIOItem>
      <DigitalIOItem Name="AcqCtrlReg1" DataType="BOOL" IOType="Output" UsedBitWidth="1" IsConnected="true">
        <Description />
      </DigitalIOItem>
      <DigitalIOItem Name="AcqCtrlReg7" DataType="BOOL" IOType="Output" UsedBitWidth="1" IsConnected="true">
        <Description />
      </DigitalIOItem>
      <DigitalIOItem Name="AcqCount" DataType="UINT" IOType="Input" UsedBitWidth="16" IsConnected="true">
        <Description />
      </DigitalIOItem>
    </IOs>
    <Description>Cognex describe how the In-Sight sensors ProfiNET capabilities are configured</Description>
  </IOGroup>
</SunriseIOGroupDescription>